[
  {
    "type": "skill",
    "subtype": "battle",
    "faction": "green",
    "id": "regeneration",
    "name": "skill.regeneration.name",
    "description": "skill.regeneration.description",
    "image": "/assets/images/skills/regeneration.png",
    "resurrectionBonus": 25,
    "attackBonus": 0,
    "defenseBonus": 0,
    "healthBonus": 0,
    "initiativeBonus": 0
  },
  {
    "type": "skill",
    "subtype": "battle",
    "faction": "black",
    "id": "leech",
    "name": "skill.leech.name",
    "description": "skill.leech.description",
    "image": "/assets/images/skills/leech.png",
    "resurrectionBonus": 0,
    "attackBonus": 0,
    "defenseBonus": 0,
    "healthBonus": 25,
    "initiativeBonus": 0
  },
  {
    "type": "skill",
    "subtype": "battle",
    "faction": "white",
    "id": "scales",
    "name": "skill.scales.name",
    "description": "skill.scales.description",
    "image": "/assets/images/skills/scales.png",
    "resurrectionBonus": 0,
    "attackBonus": 0,
    "defenseBonus": 25,
    "healthBonus": 0,
    "initiativeBonus": 0
  },
  {
    "type": "skill",
    "subtype": "battle",
    "faction": "white",
    "id": "strength",
    "name": "skill.strength.name",
    "description": "skill.strength.description",
    "image": "/assets/images/skills/strength.png",
    "resurrectionBonus": 0,
    "attackBonus": 25,
    "defenseBonus": 0,
    "healthBonus": 0,
    "initiativeBonus": 0
  },
  {
    "type": "skill",
    "subtype": "battle",
    "faction": "blue",
    "id": "haste",
    "name": "skill.haste.name",
    "description": "skill.haste.description",
    "image": "/assets/images/skills/haste.png",
    "resurrectionBonus": 0,
    "attackBonus": 0,
    "defenseBonus": 0,
    "healthBonus": 0,
    "initiativeBonus": 1
  },
  {
    "type": "skill",
    "subtype": "battle",
    "faction": "red",
    "id": "weakness",
    "name": "skill.weakness.name",
    "description": "skill.weakness.description",
    "image": "/assets/images/skills/weakness.png",
    "resurrectionBonus": 0,
    "attackBonus": 0,
    "defenseBonus": -25,
    "healthBonus": 0,
    "initiativeBonus": 0
  },
  {
    "type": "skill",
    "subtype": "battle",
    "faction": "red",
    "id": "seduction",
    "name": "skill.seduction.name",
    "description": "skill.seduction.description",
    "image": "/assets/images/skills/seduction.png",
    "resurrectionBonus": 0,
    "attackBonus": 0,
    "defenseBonus": 0,
    "healthBonus": -25,
    "initiativeBonus": 0
  },
  {
    "type": "skill",
    "subtype": "battle",
    "faction": "green",
    "id": "slowness",
    "name": "skill.slowness.name",
    "description": "skill.slowness.description",
    "image": "/assets/images/skills/slowness.png",
    "resurrectionBonus": 0,
    "attackBonus": 0,
    "defenseBonus": 0,
    "healthBonus": 0,
    "initiativeBonus": -1
  },
  {
    "type": "skill",
    "subtype": "battle",
    "faction": "blue",
    "id": "flight",
    "name": "skill.flight.name",
    "description": "skill.flight.description",
    "image": "/assets/images/skills/flight.png",
    "resurrectionBonus": 0,
    "attackBonus": 0,
    "defenseBonus": 0,
    "healthBonus": 0,
    "initiativeBonus": 2
  },
  {
    "type": "skill",
    "subtype": "battle",
    "faction": "black",
    "id": "fear",
    "name": "skill.fear.name",
    "description": "skill.fear.description",
    "image": "/assets/images/skills/fear.png",
    "resurrectionBonus": 0,
    "attackBonus": -25,
    "defenseBonus": 0,
    "healthBonus": 0,
    "initiativeBonus": 0
  }
]
